simple_loading_bar_utility/__init__.py
simple_loading_bar_utility/simple_loading_bar_utility.py
simple_loading_bar_utility-0.1.dist-info/LICENSE
simple_loading_bar_utility-0.1.dist-info/METADATA
simple_loading_bar_utility-0.1.dist-info/WHEEL
simple_loading_bar_utility-0.1.dist-info/top_level.txt
simple_loading_bar_utility-0.1.dist-info/RECORD
