Metadata-Version: 2.1
Name: simple-loading-bar-utility
Version: 0.1
Summary: A simple loading bar utility
Home-page: UNKNOWN
Author: Peter Donaghey
License: CCO 1.0
Platform: UNKNOWN
